mobidec_package_test_demo/__init__.py
mobidec_package_test_demo/main.py
mobidec_package_test_demo/divider/__init__.py
mobidec_package_test_demo/divider/divider.py
mobidec_package_test_demo/divider/divider_error.py
mobidec_package_test_demo-0.0.0.dist-info/METADATA
mobidec_package_test_demo-0.0.0.dist-info/WHEEL
mobidec_package_test_demo-0.0.0.dist-info/top_level.txt
mobidec_package_test_demo-0.0.0.dist-info/RECORD
